Abyiss/Abyiss.py
Abyiss/__init__.py
Abyiss/py.typed
Abyiss-1.0.1.dist-info/LICENSE
Abyiss-1.0.1.dist-info/METADATA
Abyiss-1.0.1.dist-info/WHEEL
Abyiss-1.0.1.dist-info/top_level.txt
Abyiss-1.0.1.dist-info/RECORD
