Metadata-Version: 2.1
Name: Abyiss
Version: 1.0.1
Summary: The Abyiss Client Library
Home-page: https://github.com/Abyiss/Client-python
Author: Abyiss
Author-email: support@abyiss.com
License: MIT
Project-URL: Documentation, https://docs.abyiss.com/
Project-URL: Abyiss, https://abyiss.com/
Project-URL: Github, https://github.com/Abyiss/Client-python
Keywords: abyiss,client,library,python,crppto,abyiss.com,data
Platform: unix
Platform: linux
Platform: osx
Platform: cygwin
Platform: win32
Classifier: Development Status :: 6 - Mature
Classifier: Topic :: Software Development :: Libraries
Classifier: Topic :: Office/Business :: Financial
Classifier: Topic :: Office/Business :: Financial :: Point-Of-Sale
Classifier: Typing :: Typed
Classifier: Topic :: Scientific/Engineering :: Artificial Life
Classifier: Topic :: Software Development
Classifier: Topic :: Database :: Database Engines/Servers
Classifier: Programming Language :: Python :: 3.6
Classifier: Programming Language :: Python :: 3 :: Only
Classifier: Topic :: Scientific/Engineering :: Information Analysis
Classifier: Programming Language :: Python :: 3.8
Classifier: Programming Language :: Python :: 3
Classifier: Topic :: Scientific/Engineering :: Electronic Design Automation (EDA)
Classifier: Topic :: Scientific/Engineering
Classifier: Topic :: Database :: Front-Ends
Classifier: Framework :: Datasette
Classifier: Programming Language :: Python :: 3.7
Classifier: Topic :: Software Development :: Libraries :: Python Modules
Classifier: Programming Language :: Python :: 3.9
Classifier: Topic :: Office/Business :: Financial :: Investment
Classifier: Topic :: Office/Business :: Financial :: Spreadsheet
Classifier: Natural Language :: English
Classifier: Topic :: Database
Requires-Python: >=3.6
License-File: LICENSE
Requires-Dist: requests
Provides-Extra: testing
Requires-Dist: pytest (>=6.0) ; extra == 'testing'
Requires-Dist: pytest-cov (>=2.0) ; extra == 'testing'
Requires-Dist: mypy (>=0.910) ; extra == 'testing'
Requires-Dist: tox (>=3.24) ; extra == 'testing'
